torch_max_backend/__init__.py
torch_max_backend/aten_functions.py
torch_max_backend/compiler.py
torch_max_backend/flags.py
torch_max_backend/testing.py
torch_max_backend-0.2.0.dist-info/METADATA
torch_max_backend-0.2.0.dist-info/WHEEL
torch_max_backend-0.2.0.dist-info/licenses/LICENSE
torch_max_backend-0.2.0.dist-info/RECORD
