Metadata-Version: 2.4
Name: torch-max-backend
Version: 0.2.0
Summary: A PyTorch backend implemented using Modular's MAX framework
Project-URL: Source, https://github.com/gabrieldemarmiesse/torch-max-backend
Project-URL: Documentation, https://gabrieldemarmiesse.github.io/torch-max-backend/
Project-URL: Bug Tracker, https://github.com/gabrieldemarmiesse/torch-max-backend/issues
License: MIT License
License-File: LICENSE
Requires-Python: >=3.11
Requires-Dist: beartype>=0.17.0
Requires-Dist: max
Requires-Dist: tabulate
Requires-Dist: torch
